{"name":"MyDeck Companion","slug":"mydeck","version":"0.0.1","icon":"./assets/icon.png","splash":{"image":"./assets/splash.png","resizeMode":"contain","backgroundColor":"#ffffff","imageUrl":"https://b3nab.github.io/mydeck/ota/assets/201a91bd1740bb1d6a1dbad049310724"},"updates":{"fallbackToCacheTimeout":0},"ios":{"supportsTablet":true},"android":{"adaptiveIcon":{"foregroundImage":"./assets/adaptive-icon.png","backgroundColor":"#FFFFFF","foregroundImageUrl":"https://b3nab.github.io/mydeck/ota/assets/97dae5a0e62ad8551d8a31897b425e63"},"package":"b3nab.mydeck.mobile"},"web":{"favicon":"./assets/favicon.png"},"sdkVersion":"42.0.0","platforms":["ios","android","web"],"currentFullName":"@anonymous/mydeck","originalFullName":"@anonymous/mydeck","locales":{},"iconUrl":"https://b3nab.github.io/mydeck/ota/assets/4e3f888fc8475f69fd5fa32f1ad5216a","bundledAssets":["asset_6a2ddad1092a0a1c326b6d0e738e682b.ttf","asset_f337aab857fd04843f0a882ec5726fb3.json","asset_2379ae894c2c9f63b852a9f3676c2763.png","asset_a970ccb3cd9a0d56fb2e49159999d02f.json"],"assetUrlOverride":"./assets","publishedTime":"2021-09-22T00:13:34.724Z","commitTime":"2021-09-22T00:13:34.724Z","releaseId":"f5291345-94aa-4941-9471-190d6a7b857f","revisionId":"6OowaLpWvQ","id":"@anonymous/mydeck","bundleUrl":"https://b3nab.github.io/mydeck/ota/bundles/ios-cbc7f37150a7c38b8bfa9217b724e943.js","platform":"ios","dependencies":["@react-native-async-storage/async-storage","expo","expo-barcode-scanner","expo-device","expo-haptics","expo-permissions","expo-status-bar","frisbee","jsondiffpatch","react","react-dom","react-native","react-native-paper","react-native-vector-icons","react-native-web","socket.io-client","styled-components"]}